setup.py
errornot/__init__.py
errornot/notifier.py
errornot/wsgi_notifier.py
errornot/tests/__init__.py
errornot/tests/test_notifier.py
errornot/tests/test_wsgi_notifier.py
errornot_notifier.egg-info/PKG-INFO
errornot_notifier.egg-info/SOURCES.txt
errornot_notifier.egg-info/dependency_links.txt
errornot_notifier.egg-info/not-zip-safe
errornot_notifier.egg-info/top_level.txt