Metadata-Version: 1.0
Name: errornot-notifier
Version: 0.1.0
Summary: ErrorNot notifier
Home-page: http://bitbucket.org/virtuo/errornot_notifier_py/wiki/Home
Author: Pierre Ruyssen (AF83)
Author-email: pierre@ruyssen.eu
License: AGPL
Keywords: errornot notifier error wsgi logging
Platform: UNKNOWN
Classifier: Development Status :: 5 - Production/Stable
Classifier: Intended Audience :: Developers
Classifier: License :: OSI Approved :: GNU Affero General Public License v3
Classifier: Programming Language :: Python
Classifier: Topic :: Internet :: WWW/HTTP :: WSGI
Classifier: Topic :: Software Development :: Quality Assurance
